dstricks2/__init__.py
dstricks2/model_metrics.py
dstricks2/py.typed
dstricks2/viz.py
dstricks2-0.1.2.dist-info/WHEEL
dstricks2-0.1.2.dist-info/METADATA
dstricks2-0.1.2.dist-info/RECORD
